{
  "totalUsersHelped": 0,
  "last24Hours": 0,
  "last7Days": 0,
  "uptimeHours": 0,
  "lastUpdated": "2026-02-05T20:12:28.637Z",
  "vmStatus": "offline",
  "source": "azure_vm",
  "history": [
    {
      "timestamp": "2026-02-05T20:12:28.637Z",
      "connections": 0,
      "total": 0
    },
    {
      "timestamp": "2026-02-05T19:20:06.732Z",
      "connections": 0,
      "total": 0
    },
    {
      "timestamp": "2026-02-05T18:24:26.927Z",
      "connections": 0,
      "total": 0
    },
    {
      "timestamp": "2026-02-05T17:22:11.315Z",
      "connections": 0,
      "total": 0
    },
    {
      "timestamp": "2026-02-05T16:20:49.391Z",
      "connections": 0,
      "total": 0
    },
    {
      "timestamp": "2026-02-05T15:22:10.780Z",
      "connections": 0,
      "total": 0
    },
    {
      "timestamp": "2026-02-05T14:23:17.068Z",
      "connections": 0,
      "total": 0
    },
    {
      "timestamp": "2026-02-05T13:33:02.883Z",
      "connections": 0,
      "total": 0
    },
    {
      "timestamp": "2026-02-05T12:18:38.220Z",
      "connections": 0,
      "total": 0
    },
    {
      "timestamp": "2026-02-05T11:18:16.079Z",
      "connections": 0,
      "total": 0
    },
    {
      "timestamp": "2026-02-05T10:19:52.399Z",
      "connections": 0,
      "total": 0
    },
    {
      "timestamp": "2026-02-05T09:21:19.127Z",
      "connections": 0,
      "total": 0
    },
    {
      "timestamp": "2026-02-05T08:19:05.922Z",
      "connections": 0,
      "total": 0
    },
    {
      "timestamp": "2026-02-05T07:26:33.904Z",
      "connections": 0,
      "total": 0
    },
    {
      "timestamp": "2026-02-05T06:26:52.144Z",
      "connections": 0,
      "total": 0
    },
    {
      "timestamp": "2026-02-05T05:30:23.764Z",
      "connections": 0,
      "total": 0
    },
    {
      "timestamp": "2026-02-05T04:39:25.246Z",
      "connections": 0,
      "total": 0
    },
    {
      "timestamp": "2026-02-05T03:05:06.311Z",
      "connections": 0,
      "total": 0
    },
    {
      "timestamp": "2026-02-05T01:39:03.058Z",
      "connections": 0,
      "total": 0
    },
    {
      "timestamp": "2026-02-05T00:38:38.234Z",
      "connections": 0,
      "total": 0
    },
    {
      "timestamp": "2026-02-04T23:10:30.053Z",
      "connections": 0,
      "total": 0
    },
    {
      "timestamp": "2026-02-04T22:08:57.193Z",
      "connections": 0,
      "total": 0
    },
    {
      "timestamp": "2026-02-04T21:14:48.524Z",
      "connections": 0,
      "total": 0
    }
  ],
  "summary": {
    "message": "Snowflake proxy stats temporarily unavailable.",
    "lastHelpedRecently": false
  }
}